[
  {
    "movie_url_id": "hexe_lilli_der_drache_und_das_magische_buch",
    "hints": [
      { "content": "A girl finds a magic book and a dragon.", "difficulty": 1, "hint_type": "PLOT" },
      { "content": "Lilli.", "difficulty": 1, "hint_type": "BIO" },
      { "content": "Hector.", "difficulty": 1, "hint_type": "BIO" },
      { "content": "Surulunda.", "difficulty": 1, "hint_type": "BIO" },
      { "content": "It was released in 2009.", "difficulty": 3, "hint_type": "TRIVIA" },
      { "content": "German film.", "difficulty": 1, "hint_type": "TRIVIA" },
      { "content": "Based on the book series by Knister.", "difficulty": 1, "hint_type": "TRIVIA" },
      { "content": "Alina Freund stars.", "difficulty": 1, "hint_type": "TRIVIA" },
      { "content": "Michael Mittermeier voices Hector.", "difficulty": 1, "hint_type": "TRIVIA" },
      { "content": "Hieronymus.", "difficulty": 2, "hint_type": "BIO" },
      { "content": "Magic.", "difficulty": 1, "hint_type": "BIO" },
      { "content": "Dragon.", "difficulty": 1, "hint_type": "BIO" },
      { "content": "Witch.", "difficulty": 1, "hint_type": "BIO" },
      { "content": "Book.", "difficulty": 1, "hint_type": "BIO" },
      { "content": "Stefan Ruzowitzky directed.", "difficulty": 2, "hint_type": "TRIVIA" },
      { "content": "Pilar Bardem stars.", "difficulty": 2, "hint_type": "TRIVIA" },
      { "content": "Ingo Naujoks stars.", "difficulty": 2, "hint_type": "TRIVIA" },
      { "content": "Anja Kling stars.", "difficulty": 2, "hint_type": "TRIVIA" },
      { "content": "Time travel.", "difficulty": 2, "hint_type": "BIO" },
      { "content": "Spells.", "difficulty": 2, "hint_type": "BIO" }
    ]
  },
  {
    "movie_url_id": "jonas_brothers_the_3d_concert_experience",
    "hints": [
      { "content": "Concert film of the Burnin' Up Tour.", "difficulty": 1, "hint_type": "PLOT" },
      { "content": "Kevin Jonas.", "difficulty": 1, "hint_type": "BIO" },
      { "content": "Joe Jonas.", "difficulty": 1, "hint_type": "BIO" },
      { "content": "Nick Jonas.", "difficulty": 1, "hint_type": "BIO" },
      { "content": "It was released in 2009.", "difficulty": 3, "hint_type": "TRIVIA" },
      { "content": "3D.", "difficulty": 1, "hint_type": "BIO" },
      { "content": "Concert.", "difficulty": 1, "hint_type": "BIO" },
      { "content": "Demi Lovato stars.", "difficulty": 1, "hint_type": "TRIVIA" },
      { "content": "Taylor Swift stars.", "difficulty": 1, "hint_type": "TRIVIA" },
      { "content": "Big Rob.", "difficulty": 2, "hint_type": "BIO" },
      { "content": "Burnin' Up.", "difficulty": 1, "hint_type": "QUOTE" },
      { "content": "S.O.S.", "difficulty": 2, "hint_type": "TRIVIA" },
      { "content": "Lovebug.", "difficulty": 2, "hint_type": "TRIVIA" },
      { "content": "Documentary.", "difficulty": 1, "hint_type": "BIO" },
      { "content": "Fans.", "difficulty": 2, "hint_type": "BIO" },
      { "content": "Backstage.", "difficulty": 2, "hint_type": "BIO" },
      { "content": "New York City.", "difficulty": 2, "hint_type": "BIO" },
      { "content": "Central Park.", "difficulty": 2, "hint_type": "BIO" },
      { "content": "Helicopter.", "difficulty": 2, "hint_type": "BIO" },
      { "content": "Music.", "difficulty": 1, "hint_type": "BIO" }
    ]
  },
  {
    "movie_url_id": "race_to_witch_mountain",
    "hints": [
      { "content": "Two alien children need to get back to their ship.", "difficulty": 1, "hint_type": "PLOT" },
      { "content": "Dwayne Johnson stars.", "difficulty": 1, "hint_type": "TRIVIA" },
      { "content": "AnnaSophia Robb stars.", "difficulty": 1, "hint_type": "TRIVIA" },
      { "content": "Alexander Ludwig stars.", "difficulty": 1, "hint_type": "TRIVIA" },
      { "content": "Jack Bruno.", "difficulty": 1, "hint_type": "BIO" },
      { "content": "Sara.", "difficulty": 1, "hint_type": "BIO" },
      { "content": "Seth.", "difficulty": 1, "hint_type": "BIO" },
      { "content": "It was released in 2009.", "difficulty": 3, "hint_type": "TRIVIA" },
      { "content": "Remake of the 1975 film.", "difficulty": 1, "hint_type": "TRIVIA" },
      { "content": "Carla Gugino stars.", "difficulty": 2, "hint_type": "TRIVIA" },
      { "content": "Dr. Alex Friedman.", "difficulty": 2, "hint_type": "BIO" },
      { "content": "Ciaran Hinds stars.", "difficulty": 2, "hint_type": "TRIVIA" },
      { "content": "Henry Burke.", "difficulty": 2, "hint_type": "BIO" },
      { "content": "Race.", "difficulty": 1, "hint_type": "QUOTE" },
      { "content": "Witch Mountain.", "difficulty": 1, "hint_type": "QUOTE" },
      { "content": "Aliens.", "difficulty": 1, "hint_type": "BIO" },
      { "content": "Taxi driver.", "difficulty": 1, "hint_type": "BIO" },
      { "content": "Las Vegas.", "difficulty": 2, "hint_type": "BIO" },
      { "content": "UFO.", "difficulty": 2, "hint_type": "BIO" },
      { "content": "Siphon.", "difficulty": 2, "hint_type": "BIO" }
    ]
  },
  {
    "movie_url_id": "hannah_montana_the_movie",
    "hints": [
      { "content": "A pop star visits her hometown to reconnect with her roots.", "difficulty": 1, "hint_type": "PLOT" },
      { "content": "Miley Cyrus stars.", "difficulty": 1, "hint_type": "TRIVIA" },
      { "content": "Billy Ray Cyrus stars.", "difficulty": 1, "hint_type": "TRIVIA" },
      { "content": "Lucas Till stars.", "difficulty": 1, "hint_type": "TRIVIA" },
      { "content": "Miley Stewart.", "difficulty": 1, "hint_type": "BIO" },
      { "content": "Hannah Montana.", "difficulty": 1, "hint_type": "BIO" },
      { "content": "Robby Ray Stewart.", "difficulty": 1, "hint_type": "BIO" },
      { "content": "Travis Brody.", "difficulty": 1, "hint_type": "BIO" },
      { "content": "It was released in 2009.", "difficulty": 3, "hint_type": "TRIVIA" },
      { "content": "Based on the TV series.", "difficulty": 1, "hint_type": "TRIVIA" },
      { "content": "Vanessa Williams stars.", "difficulty": 2, "hint_type": "TRIVIA" },
      { "content": "Vita.", "difficulty": 2, "hint_type": "BIO" },
      { "content": "Emily Osment stars.", "difficulty": 2, "hint_type": "TRIVIA" },
      { "content": "Lilly Truscott.", "difficulty": 2, "hint_type": "BIO" },
      { "content": "Jason Earles stars.", "difficulty": 2, "hint_type": "TRIVIA" },
      { "content": "Jackson Stewart.", "difficulty": 2, "hint_type": "BIO" },
      { "content": "The Climb.", "difficulty": 1, "hint_type": "TRIVIA" },
      { "content": "Tennessee.", "difficulty": 1, "hint_type": "BIO" },
      { "content": "Crowley Corners.", "difficulty": 2, "hint_type": "BIO" },
      { "content": "Hoedown Throwdown.", "difficulty": 2, "hint_type": "TRIVIA" }
    ]
  },
  {
    "movie_url_id": "earth",
    "hints": [
      { "content": "Documentary following animal families across the globe.", "difficulty": 1, "hint_type": "PLOT" },
      { "content": "James Earl Jones narrates (US).", "difficulty": 1, "hint_type": "TRIVIA" },
      { "content": "Patrick Stewart narrates (UK).", "difficulty": 1, "hint_type": "TRIVIA" },
      { "content": "It was released in 2009.", "difficulty": 3, "hint_type": "TRIVIA" },
      { "content": "Disneynature.", "difficulty": 1, "hint_type": "TRIVIA" },
      { "content": "Earth.", "difficulty": 1, "hint_type": "QUOTE" },
      { "content": "Polar bear.", "difficulty": 1, "hint_type": "BIO" },
      { "content": "Elephant.", "difficulty": 1, "hint_type": "BIO" },
      { "content": "Humpback whale.", "difficulty": 1, "hint_type": "BIO" },
      { "content": "Migration.", "difficulty": 1, "hint_type": "BIO" },
      { "content": "Seasons.", "difficulty": 1, "hint_type": "BIO" },
      { "content": "Sun.", "difficulty": 2, "hint_type": "BIO" },
      { "content": "Arctic.", "difficulty": 2, "hint_type": "BIO" },
      { "content": "Kalahari.", "difficulty": 2, "hint_type": "BIO" },
      { "content": "Tropics.", "difficulty": 2, "hint_type": "BIO" },
      { "content": "Documentary.", "difficulty": 1, "hint_type": "BIO" },
      { "content": "Nature.", "difficulty": 1, "hint_type": "BIO" },
      { "content": "Alastair Fothergill directed.", "difficulty": 2, "hint_type": "TRIVIA" },
      { "content": "Mark Linfield directed.", "difficulty": 2, "hint_type": "TRIVIA" },
      { "content": "Planet Earth.", "difficulty": 2, "hint_type": "TRIVIA" }
    ]
  },
  {
    "movie_url_id": "trail_of_the_panda",
    "hints": [
      { "content": "A boy rescues an orphaned panda cub.", "difficulty": 1, "hint_type": "PLOT" },
      { "content": "Lu.", "difficulty": 1, "hint_type": "BIO" },
      { "content": "Panda.", "difficulty": 1, "hint_type": "BIO" },
      { "content": "It was released in 2009.", "difficulty": 3, "hint_type": "TRIVIA" },
      { "content": "Chinese film.", "difficulty": 1, "hint_type": "TRIVIA" },
      { "content": "Trail.", "difficulty": 1, "hint_type": "QUOTE" },
      { "content": "Cub.", "difficulty": 1, "hint_type": "BIO" },
      { "content": "Researcher.", "difficulty": 2, "hint_type": "BIO" },
      { "content": "Forest.", "difficulty": 1, "hint_type": "BIO" },
      { "content": "Orphan.", "difficulty": 1, "hint_type": "BIO" },
      { "content": "Daichi Harashima stars.", "difficulty": 2, "hint_type": "TRIVIA" },
      { "content": "Feng.", "difficulty": 2, "hint_type": "BIO" },
      { "content": "Zhang Qi stars.", "difficulty": 2, "hint_type": "TRIVIA" },
      { "content": "Adventure.", "difficulty": 1, "hint_type": "BIO" },
      { "content": "Nature.", "difficulty": 1, "hint_type": "BIO" },
      { "content": "Rescue.", "difficulty": 1, "hint_type": "BIO" },
      { "content": "Friendship.", "difficulty": 1, "hint_type": "BIO" },
      { "content": "Mountain.", "difficulty": 2, "hint_type": "BIO" },
      { "content": "Scientist.", "difficulty": 2, "hint_type": "BIO" },
      { "content": "Separation.", "difficulty": 2, "hint_type": "BIO" }
    ]
  },
  {
    "movie_url_id": "the_boys_the_sherman_brothers_story",
    "hints": [
      { "content": "Documentary about the songwriting duo.", "difficulty": 1, "hint_type": "PLOT" },
      { "content": "Richard M. Sherman.", "difficulty": 1, "hint_type": "BIO" },
      { "content": "Robert B. Sherman.", "difficulty": 1, "hint_type": "BIO" },
      { "content": "It was released in 2009.", "difficulty": 3, "hint_type": "TRIVIA" },
      { "content": "Sherman Brothers.", "difficulty": 1, "hint_type": "BIO" },
      { "content": "Songwriters.", "difficulty": 1, "hint_type": "BIO" },
      { "content": "Mary Poppins.", "difficulty": 1, "hint_type": "TRIVIA" },
      { "content": "The Jungle Book.", "difficulty": 1, "hint_type": "TRIVIA" },
      { "content": "Chitty Chitty Bang Bang.", "difficulty": 1, "hint_type": "TRIVIA" },
      { "content": "It's a Small World.", "difficulty": 1, "hint_type": "TRIVIA" },
      { "content": "Boys.", "difficulty": 1, "hint_type": "QUOTE" },
      { "content": "Story.", "difficulty": 1, "hint_type": "QUOTE" },
      { "content": "Documentary.", "difficulty": 1, "hint_type": "BIO" },
      { "content": "Brothers.", "difficulty": 1, "hint_type": "BIO" },
      { "content": "Estrangement.", "difficulty": 2, "hint_type": "BIO" },
      { "content": "Walt Disney.", "difficulty": 2, "hint_type": "BIO" },
      { "content": "Music.", "difficulty": 1, "hint_type": "BIO" },
      { "content": "Jeffrey C. Sherman directed.", "difficulty": 2, "hint_type": "TRIVIA" },
      { "content": "Gregory V. Sherman directed.", "difficulty": 2, "hint_type": "TRIVIA" },
      { "content": "Academy Awards.", "difficulty": 2, "hint_type": "BIO" }
    ]
  },
  {
    "movie_url_id": "up",
    "hints": [
      { "content": "An old man flies his house to South America.", "difficulty": 1, "hint_type": "PLOT" },
      { "content": "Carl Fredricksen.", "difficulty": 1, "hint_type": "BIO" },
      { "content": "Russell.", "difficulty": 1, "hint_type": "BIO" },
      { "content": "Dug.", "difficulty": 1, "hint_type": "BIO" },
      { "content": "Kevin.", "difficulty": 1, "hint_type": "BIO" },
      { "content": "Charles Muntz.", "difficulty": 1, "hint_type": "BIO" },
      { "content": "Ellie.", "difficulty": 1, "hint_type": "BIO" },
      { "content": "It was released in 2009.", "difficulty": 3, "hint_type": "TRIVIA" },
      { "content": "Pixar.", "difficulty": 1, "hint_type": "TRIVIA" },
      { "content": "Ed Asner voices Carl.", "difficulty": 1, "hint_type": "TRIVIA" },
      { "content": "Jordan Nagai voices Russell.", "difficulty": 2, "hint_type": "TRIVIA" },
      { "content": "Christopher Plummer voices Muntz.", "difficulty": 2, "hint_type": "TRIVIA" },
      { "content": "Bob Peterson voices Dug.", "difficulty": 2, "hint_type": "TRIVIA" },
      { "content": "Up.", "difficulty": 1, "hint_type": "QUOTE" },
      { "content": "Balloons.", "difficulty": 1, "hint_type": "BIO" },
      { "content": "Paradise Falls.", "difficulty": 1, "hint_type": "BIO" },
      { "content": "Squirrel!", "difficulty": 1, "hint_type": "QUOTE" },
      { "content": "Adventure is out there!", "difficulty": 1, "hint_type": "QUOTE" },
      { "content": "Grape soda badge.", "difficulty": 2, "hint_type": "BIO" },
      { "content": "Cone of shame.", "difficulty": 2, "hint_type": "BIO" }
    ]
  },
  {
    "movie_url_id": "the_proposal",
    "hints": [
      { "content": "A boss forces her assistant to marry her.", "difficulty": 1, "hint_type": "PLOT" },
      { "content": "Sandra Bullock stars.", "difficulty": 1, "hint_type": "TRIVIA" },
      { "content": "Ryan Reynolds stars.", "difficulty": 1, "hint_type": "TRIVIA" },
      { "content": "Betty White stars.", "difficulty": 1, "hint_type": "TRIVIA" },
      { "content": "Margaret Tate.", "difficulty": 1, "hint_type": "BIO" },
      { "content": "Andrew Paxton.", "difficulty": 1, "hint_type": "BIO" },
      { "content": "Grandma Annie.", "difficulty": 1, "hint_type": "BIO" },
      { "content": "It was released in 2009.", "difficulty": 3, "hint_type": "TRIVIA" },
      { "content": "Released under Touchstone Pictures.", "difficulty": 2, "hint_type": "TRIVIA" },
      { "content": "Proposal.", "difficulty": 1, "hint_type": "QUOTE" },
      { "content": "Alaska.", "difficulty": 1, "hint_type": "BIO" },
      { "content": "Deportation.", "difficulty": 1, "hint_type": "BIO" },
      { "content": "Canada.", "difficulty": 2, "hint_type": "BIO" },
      { "content": "Mary Steenburgen stars.", "difficulty": 2, "hint_type": "TRIVIA" },
      { "content": "Craig T. Nelson stars.", "difficulty": 2, "hint_type": "TRIVIA" },
      { "content": "Ramone.", "difficulty": 2, "hint_type": "BIO" },
      { "content": "Oscar Nunez stars.", "difficulty": 2, "hint_type": "TRIVIA" },
      { "content": "Eagle.", "difficulty": 2, "hint_type": "BIO" },
      { "content": "Blanket.", "difficulty": 2, "hint_type": "BIO" },
      { "content": "Romance comedy.", "difficulty": 1, "hint_type": "BIO" }
    ]
  },
  {
    "movie_url_id": "gforce",
    "hints": [
      { "content": "Guinea pigs work as secret agents.", "difficulty": 1, "hint_type": "PLOT" },
      { "content": "Darwin.", "difficulty": 1, "hint_type": "BIO" },
      { "content": "Blaster.", "difficulty": 1, "hint_type": "BIO" },
      { "content": "Juarez.", "difficulty": 1, "hint_type": "BIO" },
      { "content": "Speckles.", "difficulty": 1, "hint_type": "BIO" },
      { "content": "Mooch.", "difficulty": 1, "hint_type": "BIO" },
      { "content": "It was released in 2009.", "difficulty": 3, "hint_type": "TRIVIA" },
      { "content": "Sam Rockwell voices Darwin.", "difficulty": 1, "hint_type": "TRIVIA" },
      { "content": "Tracy Morgan voices Blaster.", "difficulty": 1, "hint_type": "TRIVIA" },
      { "content": "Penelope Cruz voices Juarez.", "difficulty": 1, "hint_type": "TRIVIA" },
      { "content": "Nicolas Cage voices Speckles.", "difficulty": 1, "hint_type": "TRIVIA" },
      { "content": "G-Force.", "difficulty": 1, "hint_type": "QUOTE" },
      { "content": "Guinea pig.", "difficulty": 1, "hint_type": "BIO" },
      { "content": "Mole.", "difficulty": 1, "hint_type": "BIO" },
      { "content": "Fly.", "difficulty": 2, "hint_type": "BIO" },
      { "content": "Zach Galifianakis stars.", "difficulty": 2, "hint_type": "TRIVIA" },
      { "content": "Ben.", "difficulty": 2, "hint_type": "BIO" },
      { "content": "Bill Nighy stars.", "difficulty": 2, "hint_type": "TRIVIA" },
      { "content": "Saber.", "difficulty": 2, "hint_type": "BIO" },
      { "content": "Appliances.", "difficulty": 2, "hint_type": "BIO" }
    ]
  },
  {
    "movie_url_id": "ponyo",
    "hints": [
      { "content": "A goldfish princess wants to become human.", "difficulty": 1, "hint_type": "PLOT" },
      { "content": "Ponyo.", "difficulty": 1, "hint_type": "BIO" },
      { "content": "Sosuke.", "difficulty": 1, "hint_type": "BIO" },
      { "content": "Fujimoto.", "difficulty": 1, "hint_type": "BIO" },
      { "content": "Granmamare.", "difficulty": 1, "hint_type": "BIO" },
      { "content": "Lisa.", "difficulty": 1, "hint_type": "BIO" },
      { "content": "It was released in 2009.", "difficulty": 3, "hint_type": "TRIVIA" },
      { "content": "Studio Ghibli.", "difficulty": 1, "hint_type": "TRIVIA" },
      { "content": "Hayao Miyazaki directed.", "difficulty": 1, "hint_type": "TRIVIA" },
      { "content": "Noah Cyrus voices Ponyo.", "difficulty": 2, "hint_type": "TRIVIA" },
      { "content": "Frankie Jonas voices Sosuke.", "difficulty": 2, "hint_type": "TRIVIA" },
      { "content": "Liam Neeson voices Fujimoto.", "difficulty": 2, "hint_type": "TRIVIA" },
      { "content": "Tina Fey voices Lisa.", "difficulty": 2, "hint_type": "TRIVIA" },
      { "content": "Cate Blanchett voices Granmamare.", "difficulty": 2, "hint_type": "TRIVIA" },
      { "content": "Fish.", "difficulty": 1, "hint_type": "BIO" },
      { "content": "Ocean.", "difficulty": 1, "hint_type": "BIO" },
      { "content": "Ham.", "difficulty": 2, "hint_type": "BIO" },
      { "content": "Bucket.", "difficulty": 2, "hint_type": "BIO" },
      { "content": "Tsunami.", "difficulty": 2, "hint_type": "BIO" },
      { "content": "Magic.", "difficulty": 1, "hint_type": "BIO" }
    ]
  },
  {
    "movie_url_id": "xgames_3d_the_movie",
    "hints": [
      { "content": "Documentary about the X Games.", "difficulty": 1, "hint_type": "PLOT" },
      { "content": "Shaun White.", "difficulty": 1, "hint_type": "BIO" },
      { "content": "Travis Pastrana.", "difficulty": 1, "hint_type": "BIO" },
      { "content": "Ricky Carmichael.", "difficulty": 1, "hint_type": "BIO" },
      { "content": "Bob Burnquist.", "difficulty": 1, "hint_type": "BIO" },
      { "content": "Danny Way.", "difficulty": 1, "hint_type": "BIO" },
      { "content": "It was released in 2009.", "difficulty": 3, "hint_type": "TRIVIA" },
      { "content": "3D.", "difficulty": 1, "hint_type": "BIO" },
      { "content": "X Games.", "difficulty": 1, "hint_type": "QUOTE" },
      { "content": "Skateboarding.", "difficulty": 1, "hint_type": "BIO" },
      { "content": "Motocross.", "difficulty": 1, "hint_type": "BIO" },
      { "content": "BMX.", "difficulty": 1, "hint_type": "BIO" },
      { "content": "Rally car.", "difficulty": 1, "hint_type": "BIO" },
      { "content": "Documentary.", "difficulty": 1, "hint_type": "BIO" },
      { "content": "Sports.", "difficulty": 1, "hint_type": "BIO" },
      { "content": "Extreme.", "difficulty": 1, "hint_type": "BIO" },
      { "content": "Kyle Kyle.", "difficulty": 2, "hint_type": "BIO" },
      { "content": "Jake Brown.", "difficulty": 2, "hint_type": "BIO" },
      { "content": "Mega Ramp.", "difficulty": 2, "hint_type": "BIO" },
      { "content": "Emile Hirsch narrates.", "difficulty": 2, "hint_type": "TRIVIA" }
    ]
  },
  {
    "movie_url_id": "walt_el_grupo",
    "hints": [
      { "content": "Documentary about Walt Disney's trip to South America.", "difficulty": 1, "hint_type": "PLOT" },
      { "content": "Walt Disney.", "difficulty": 1, "hint_type": "BIO" },
      { "content": "El Grupo.", "difficulty": 1, "hint_type": "QUOTE" },
      { "content": "South America.", "difficulty": 1, "hint_type": "BIO" },
      { "content": "It was released in 2009.", "difficulty": 3, "hint_type": "TRIVIA" },
      { "content": "1941.", "difficulty": 1, "hint_type": "BIO" },
      { "content": "Goodwill tour.", "difficulty": 1, "hint_type": "BIO" },
      { "content": "Mary Blair.", "difficulty": 2, "hint_type": "BIO" },
      { "content": "Frank Thomas.", "difficulty": 2, "hint_type": "BIO" },
      { "content": "Norm Ferguson.", "difficulty": 2, "hint_type": "BIO" },
      { "content": "Saludos Amigos.", "difficulty": 1, "hint_type": "TRIVIA" },
      { "content": "The Three Caballeros.", "difficulty": 1, "hint_type": "TRIVIA" },
      { "content": "Documentary.", "difficulty": 1, "hint_type": "BIO" },
      { "content": "Brazil.", "difficulty": 2, "hint_type": "BIO" },
      { "content": "Argentina.", "difficulty": 2, "hint_type": "BIO" },
      { "content": "Chile.", "difficulty": 2, "hint_type": "BIO" },
      { "content": "Peru.", "difficulty": 2, "hint_type": "BIO" },
      { "content": "Ted Thomas directed.", "difficulty": 2, "hint_type": "TRIVIA" },
      { "content": "Artists.", "difficulty": 1, "hint_type": "BIO" },
      { "content": "Inspiration.", "difficulty": 1, "hint_type": "BIO" }
    ]
  },
  {
    "movie_url_id": "surrogates",
    "hints": [
      { "content": "People live through robot surrogates.", "difficulty": 1, "hint_type": "PLOT" },
      { "content": "Bruce Willis stars.", "difficulty": 1, "hint_type": "TRIVIA" },
      { "content": "Radha Mitchell stars.", "difficulty": 1, "hint_type": "TRIVIA" },
      { "content": "Rosamund Pike stars.", "difficulty": 1, "hint_type": "TRIVIA" },
      { "content": "Tom Greer.", "difficulty": 1, "hint_type": "BIO" },
      { "content": "Jennifer Peters.", "difficulty": 1, "hint_type": "BIO" },
      { "content": "Maggie Greer.", "difficulty": 1, "hint_type": "BIO" },
      { "content": "It was released in 2009.", "difficulty": 3, "hint_type": "TRIVIA" },
      { "content": "Released under Touchstone Pictures.", "difficulty": 2, "hint_type": "TRIVIA" },
      { "content": "Ving Rhames stars.", "difficulty": 2, "hint_type": "TRIVIA" },
      { "content": "The Prophet.", "difficulty": 2, "hint_type": "BIO" },
      { "content": "Surrogates.", "difficulty": 1, "hint_type": "QUOTE" },
      { "content": "Robots.", "difficulty": 1, "hint_type": "BIO" },
      { "content": "Murder.", "difficulty": 1, "hint_type": "BIO" },
      { "content": "James Cromwell stars.", "difficulty": 2, "hint_type": "TRIVIA" },
      { "content": "Canter.", "difficulty": 2, "hint_type": "BIO" },
      { "content": "Sci-fi thriller.", "difficulty": 1, "hint_type": "BIO" },
      { "content": "Chair.", "difficulty": 2, "hint_type": "BIO" },
      { "content": "Operator.", "difficulty": 2, "hint_type": "BIO" },
      { "content": "Weapon.", "difficulty": 2, "hint_type": "BIO" }
    ]
  },
  {
    "movie_url_id": "tinker_bell_and_the_lost_treasure",
    "hints": [
      { "content": "Tinker Bell goes on a quest to find a lost treasure.", "difficulty": 1, "hint_type": "PLOT" },
      { "content": "Tinker Bell.", "difficulty": 1, "hint_type": "BIO" },
      { "content": "Terence.", "difficulty": 1, "hint_type": "BIO" },
      { "content": "Blaze.", "difficulty": 1, "hint_type": "BIO" },
      { "content": "It was released in 2009.", "difficulty": 3, "hint_type": "TRIVIA" },
      { "content": "Mae Whitman voices Tinker Bell.", "difficulty": 1, "hint_type": "TRIVIA" },
      { "content": "Jesse McCartney voices Terence.", "difficulty": 1, "hint_type": "TRIVIA" },
      { "content": "Lost Treasure.", "difficulty": 1, "hint_type": "QUOTE" },
      { "content": "Moonstone.", "difficulty": 1, "hint_type": "BIO" },
      { "content": "Scepter.", "difficulty": 1, "hint_type": "BIO" },
      { "content": "Pixie Dust.", "difficulty": 1, "hint_type": "BIO" },
      { "content": "Balloon.", "difficulty": 2, "hint_type": "BIO" },
      { "content": "Mirror.", "difficulty": 2, "hint_type": "BIO" },
      { "content": "Trolls.", "difficulty": 2, "hint_type": "BIO" },
      { "content": "Fairy.", "difficulty": 1, "hint_type": "BIO" },
      { "content": "Friendship.", "difficulty": 1, "hint_type": "BIO" },
      { "content": "Autumn.", "difficulty": 2, "hint_type": "BIO" },
      { "content": "Blue Harvest Moon.", "difficulty": 2, "hint_type": "BIO" },
      { "content": "Cotton puff.", "difficulty": 2, "hint_type": "BIO" },
      { "content": "Firefly.", "difficulty": 2, "hint_type": "BIO" }
    ]
  },
  {
    "movie_url_id": "kniga_masterov_the_book_of_masters",
    "hints": [
      { "content": "A young man must save the world from the Stone Princess.", "difficulty": 1, "hint_type": "PLOT" },
      { "content": "Ivan.", "difficulty": 1, "hint_type": "BIO" },
      { "content": "Katya.", "difficulty": 1, "hint_type": "BIO" },
      { "content": "Stone Princess.", "difficulty": 1, "hint_type": "BIO" },
      { "content": "It was released in 2009.", "difficulty": 3, "hint_type": "TRIVIA" },
      { "content": "Russian film.", "difficulty": 1, "hint_type": "TRIVIA" },
      { "content": "First Disney film produced in Russia.", "difficulty": 1, "hint_type": "TRIVIA" },
      { "content": "Book of Masters.", "difficulty": 1, "hint_type": "QUOTE" },
      { "content": "Magic.", "difficulty": 1, "hint_type": "BIO" },
      { "content": "Stone.", "difficulty": 1, "hint_type": "BIO" },
      { "content": "Baba Yaga.", "difficulty": 2, "hint_type": "BIO" },
      { "content": "Mermaid.", "difficulty": 2, "hint_type": "BIO" },
      { "content": "Mirror.", "difficulty": 2, "hint_type": "BIO" },
      { "content": "Alatyr.", "difficulty": 2, "hint_type": "BIO" },
      { "content": "Carving.", "difficulty": 2, "hint_type": "BIO" },
      { "content": "Maxim Loktionov stars.", "difficulty": 2, "hint_type": "TRIVIA" },
      { "content": "Mariya Andreeva stars.", "difficulty": 2, "hint_type": "TRIVIA" },
      { "content": "Irina Apeksimova stars.", "difficulty": 2, "hint_type": "TRIVIA" },
      { "content": "Fairytale.", "difficulty": 1, "hint_type": "BIO" },
      { "content": "Tower.", "difficulty": 2, "hint_type": "BIO" }
    ]
  },
  {
    "movie_url_id": "disneys_a_christmas_carol",
    "hints": [
      { "content": "A miser is visited by three ghosts on Christmas Eve.", "difficulty": 1, "hint_type": "PLOT" },
      { "content": "Jim Carrey stars.", "difficulty": 1, "hint_type": "TRIVIA" },
      { "content": "Ebenezer Scrooge.", "difficulty": 1, "hint_type": "BIO" },
      { "content": "Bob Cratchit.", "difficulty": 1, "hint_type": "BIO" },
      { "content": "Tiny Tim.", "difficulty": 1, "hint_type": "BIO" },
      { "content": "Jacob Marley.", "difficulty": 1, "hint_type": "BIO" },
      { "content": "It was released in 2009.", "difficulty": 3, "hint_type": "TRIVIA" },
      { "content": "Robert Zemeckis directed.", "difficulty": 1, "hint_type": "TRIVIA" },
      { "content": "Gary Oldman stars.", "difficulty": 2, "hint_type": "TRIVIA" },
      { "content": "Colin Firth stars.", "difficulty": 2, "hint_type": "TRIVIA" },
      { "content": "Fred.", "difficulty": 2, "hint_type": "BIO" },
      { "content": "Christmas Carol.", "difficulty": 1, "hint_type": "QUOTE" },
      { "content": "Ghost of Christmas Past.", "difficulty": 1, "hint_type": "BIO" },
      { "content": "Ghost of Christmas Present.", "difficulty": 1, "hint_type": "BIO" },
      { "content": "Ghost of Christmas Yet to Come.", "difficulty": 1, "hint_type": "BIO" },
      { "content": "Humbug.", "difficulty": 1, "hint_type": "QUOTE" },
      { "content": "Motion capture.", "difficulty": 1, "hint_type": "BIO" },
      { "content": "Fezziwig.", "difficulty": 2, "hint_type": "BIO" },
      { "content": "Belle.", "difficulty": 2, "hint_type": "BIO" },
      { "content": "London.", "difficulty": 2, "hint_type": "BIO" }
    ]
  },
  {
    "movie_url_id": "old_dogs",
    "hints": [
      { "content": "Two friends have to take care of 7-year-old twins.", "difficulty": 1, "hint_type": "PLOT" },
      { "content": "John Travolta stars.", "difficulty": 1, "hint_type": "TRIVIA" },
      { "content": "Robin Williams stars.", "difficulty": 1, "hint_type": "TRIVIA" },
      { "content": "Kelly Preston stars.", "difficulty": 1, "hint_type": "TRIVIA" },
      { "content": "Charlie Reed.", "difficulty": 1, "hint_type": "BIO" },
      { "content": "Dan Rayburn.", "difficulty": 1, "hint_type": "BIO" },
      { "content": "Vicki Greer.", "difficulty": 1, "hint_type": "BIO" },
      { "content": "It was released in 2009.", "difficulty": 3, "hint_type": "TRIVIA" },
      { "content": "Ella Bleu Travolta stars.", "difficulty": 2, "hint_type": "TRIVIA" },
      { "content": "Emily.", "difficulty": 2, "hint_type": "BIO" },
      { "content": "Zach.", "difficulty": 2, "hint_type": "BIO" },
      { "content": "Seth Green stars.", "difficulty": 2, "hint_type": "TRIVIA" },
      { "content": "Ralph White.", "difficulty": 2, "hint_type": "BIO" },
      { "content": "Old.", "difficulty": 1, "hint_type": "QUOTE" },
      { "content": "Dogs.", "difficulty": 1, "hint_type": "QUOTE" },
      { "content": "Camping.", "difficulty": 2, "hint_type": "BIO" },
      { "content": "Zoo.", "difficulty": 2, "hint_type": "BIO" },
      { "content": "Gorilla.", "difficulty": 2, "hint_type": "BIO" },
      { "content": "Penguins.", "difficulty": 2, "hint_type": "BIO" },
      { "content": "Comedy.", "difficulty": 1, "hint_type": "BIO" }
    ]
  },
  {
    "movie_url_id": "the_princess_and_the_frog",
    "hints": [
      { "content": "A waitress kisses a frog prince and turns into a frog.", "difficulty": 1, "hint_type": "PLOT" },
      { "content": "Tiana.", "difficulty": 1, "hint_type": "BIO" },
      { "content": "Prince Naveen.", "difficulty": 1, "hint_type": "BIO" },
      { "content": "Dr. Facilier.", "difficulty": 1, "hint_type": "BIO" },
      { "content": "Louis.", "difficulty": 1, "hint_type": "BIO" },
      { "content": "Ray.", "difficulty": 1, "hint_type": "BIO" },
      { "content": "Mama Odie.", "difficulty": 1, "hint_type": "BIO" },
      { "content": "Charlotte La Bouff.", "difficulty": 1, "hint_type": "BIO" },
      { "content": "It was released in 2009.", "difficulty": 3, "hint_type": "TRIVIA" },
      { "content": "New Orleans.", "difficulty": 1, "hint_type": "BIO" },
      { "content": "Princess.", "difficulty": 1, "hint_type": "QUOTE" },
      { "content": "Frog.", "difficulty": 1, "hint_type": "QUOTE" },
      { "content": "Anika Noni Rose voices Tiana.", "difficulty": 1, "hint_type": "TRIVIA" },
      { "content": "Keith David voices Dr. Facilier.", "difficulty": 2, "hint_type": "TRIVIA" },
      { "content": "Shadow Man.", "difficulty": 2, "hint_type": "BIO" },
      { "content": "Restaurant.", "difficulty": 1, "hint_type": "BIO" },
      { "content": "Gumbo.", "difficulty": 2, "hint_type": "BIO" },
      { "content": "Evangeline.", "difficulty": 2, "hint_type": "BIO" },
      { "content": "Jazz.", "difficulty": 1, "hint_type": "BIO" },
      { "content": "Bayou.", "difficulty": 1, "hint_type": "BIO" }
    ]
  },
  {
    "movie_url_id": "when_in_rome",
    "hints": [
      { "content": "A woman steals coins from a fountain and is pursued by suitors.", "difficulty": 1, "hint_type": "PLOT" },
      { "content": "Kristen Bell stars.", "difficulty": 1, "hint_type": "TRIVIA" },
      { "content": "Josh Duhamel stars.", "difficulty": 1, "hint_type": "TRIVIA" },
      { "content": "Beth Martin.", "difficulty": 1, "hint_type": "BIO" },
      { "content": "Nick Beamon.", "difficulty": 1, "hint_type": "BIO" },
      { "content": "It was released in 2010.", "difficulty": 3, "hint_type": "TRIVIA" },
      { "content": "Released under Touchstone Pictures.", "difficulty": 2, "hint_type": "TRIVIA" },
      { "content": "Will Arnett stars.", "difficulty": 2, "hint_type": "TRIVIA" },
      { "content": "Jon Heder stars.", "difficulty": 2, "hint_type": "TRIVIA" },
      { "content": "Dax Shepard stars.", "difficulty": 2, "hint_type": "TRIVIA" },
      { "content": "Danny DeVito stars.", "difficulty": 2, "hint_type": "TRIVIA" },
      { "content": "Anjelica Huston stars.", "difficulty": 2, "hint_type": "TRIVIA" },
      { "content": "Rome.", "difficulty": 1, "hint_type": "QUOTE" },
      { "content": "Fountain of Love.", "difficulty": 1, "hint_type": "BIO" },
      { "content": "Coins.", "difficulty": 1, "hint_type": "BIO" },
      { "content": "Magic.", "difficulty": 1, "hint_type": "BIO" },
      { "content": "Guggenheim.", "difficulty": 2, "hint_type": "BIO" },
      { "content": "Curator.", "difficulty": 2, "hint_type": "BIO" },
      { "content": "Wedding.", "difficulty": 2, "hint_type": "BIO" },
      { "content": "Romance comedy.", "difficulty": 1, "hint_type": "BIO" }
    ]
  }
]
